codedump/__init__.py
codedump/codedump.py
codedump-1.0.0.dist-info/LICENSE
codedump-1.0.0.dist-info/METADATA
codedump-1.0.0.dist-info/WHEEL
codedump-1.0.0.dist-info/entry_points.txt
codedump-1.0.0.dist-info/top_level.txt
codedump-1.0.0.dist-info/RECORD
